ch1p/__init__.py
ch1p/functions.py
ch1p/state.py
ch1p-0.0.7.dist-info/LICENSE
ch1p-0.0.7.dist-info/METADATA
ch1p-0.0.7.dist-info/WHEEL
ch1p-0.0.7.dist-info/top_level.txt
ch1p-0.0.7.dist-info/RECORD
