Metadata-Version: 2.1
Name: ch1p
Version: 0.0.7
Summary: UNKNOWN
Home-page: https://github.com/gch1p/ch1p-py.git
Author: Evgeny Zinoviev
Author-email: me@ch1p.io
License: BSD
Project-URL: Bug Tracker, https://github.com/gch1p/ch1p-py/issues
Platform: UNKNOWN
Classifier: Programming Language :: Python :: 3
Classifier: License :: OSI Approved :: BSD License
Classifier: Operating System :: OS Independent
Requires-Python: >=3.6
License-File: LICENSE
Requires-Dist: requests
